[
    [
        "format_version", 
        "2.1"
    ], 
    [
        "pymorphy2_version", 
        "0.3.3"
    ], 
    [
        "compiled_at", 
        "2013-04-23T19:49:26.231686"
    ], 
    [
        "source", 
        "opencorpora.org"
    ], 
    [
        "source_version", 
        "0.92"
    ], 
    [
        "source_revision", 
        "389658"
    ], 
    [
        "source_lexemes_count", 
        388659
    ], 
    [
        "source_links_count", 
        256549
    ], 
    [
        "gramtab_length", 
        4427
    ], 
    [
        "gramtab_formats", 
        {
            "opencorpora-int": "gramtab-opencorpora-int.json", 
            "opencorpora-ext": "gramtab-opencorpora-ext.json"
        }
    ], 
    [
        "paradigms_length", 
        2970
    ], 
    [
        "suffixes_length", 
        14520
    ], 
    [
        "words_dawg_length", 
        5092985
    ], 
    [
        "prediction_options", 
        {
            "min_paradigm_popularity": 3, 
            "max_suffix_length": 5, 
            "min_ending_freq": 2
        }
    ], 
    [
        "prediction_suffixes_dawg_lengths", 
        [
            364190, 
            1927, 
            21
        ]
    ], 
    [
        "prediction_prefixes_dawg_length", 
        144
    ], 
    [
        "paradigm_prefixes_length", 
        3
    ]
]